ollash/__init__.py
ollash/__main__.py
ollash/commands.py
ollash/config.py
ollash/config.yaml
ollash/embedding_utils.py
ollash/history.py
ollash/menu_advanced.py
ollash/ollama_nl2bash.py
ollash/progress.py
ollash/shell.py
ollash/ui.py
ollash/utils.py
tests/__init__.py
tests/test_cli.py
tests/test_ollama.py
tests/test_utils.py
ollash-1.0.2.dist-info/METADATA
ollash-1.0.2.dist-info/WHEEL
ollash-1.0.2.dist-info/entry_points.txt
ollash-1.0.2.dist-info/top_level.txt
ollash-1.0.2.dist-info/RECORD
