Metadata-Version: 2.4
Name: ollash
Version: 1.0.2
Summary: Convert natural language into safe Terminal commands using Ollama.
Home-page: https://github.com/team-chocos/ollash
Author: Team-Chocos
Author-email: teamcornflakesxx@gmail.com
Classifier: Programming Language :: Python :: 3
Classifier: License :: OSI Approved :: MIT License
Classifier: Operating System :: POSIX :: Linux
Classifier: Topic :: Utilities
Requires-Python: >=3.7
Requires-Dist: platformdirs
Requires-Dist: pyyaml
Requires-Dist: tqdm
Requires-Dist: inquirer
Requires-Dist: interro
Requires-Dist: pyfzf
Dynamic: author
Dynamic: author-email
Dynamic: classifier
Dynamic: description
Dynamic: description-content-type
Dynamic: home-page
Dynamic: requires-dist
Dynamic: requires-python
Dynamic: summary
